edx_name_affirmation/__init__.py
edx_name_affirmation/admin.py
edx_name_affirmation/api.py
edx_name_affirmation/apps.py
edx_name_affirmation/exceptions.py
edx_name_affirmation/handlers.py
edx_name_affirmation/models.py
edx_name_affirmation/name_change_validator.py
edx_name_affirmation/serializers.py
edx_name_affirmation/services.py
edx_name_affirmation/signals.py
edx_name_affirmation/statuses.py
edx_name_affirmation/tasks.py
edx_name_affirmation/urls.py
edx_name_affirmation/views.py
edx_name_affirmation/conf/locale/config.yaml
edx_name_affirmation/migrations/0001_initial.py
edx_name_affirmation/migrations/0002_verifiednameconfig.py
edx_name_affirmation/migrations/0003_verifiedname_status.py
edx_name_affirmation/migrations/0004_auto_20210816_0958.py
edx_name_affirmation/migrations/0005_remove_verifiedname_is_verified.py
edx_name_affirmation/migrations/0006_auto_20210830_2029.py
edx_name_affirmation/migrations/0007_historicalverifiedname.py
edx_name_affirmation/migrations/0008_alter_historicalverifiedname_options.py
edx_name_affirmation/migrations/0009_add_verifiedname_platform_verification_id.py
edx_name_affirmation/migrations/0010_alter_historicalverifiedname_options.py
edx_name_affirmation/migrations/__init__.py
edx_name_affirmation/tests/__init__.py
edx_name_affirmation/tests/test_api.py
edx_name_affirmation/tests/test_handlers.py
edx_name_affirmation/tests/test_models.py
edx_name_affirmation/tests/test_name_change_validator.py
edx_name_affirmation/tests/test_services.py
edx_name_affirmation/tests/test_signals.py
edx_name_affirmation/tests/test_tasks.py
edx_name_affirmation/tests/test_views.py
edx_name_affirmation/tests/utils.py
edx_name_affirmation-3.0.2.dist-info/LICENSE
edx_name_affirmation-3.0.2.dist-info/METADATA
edx_name_affirmation-3.0.2.dist-info/WHEEL
edx_name_affirmation-3.0.2.dist-info/entry_points.txt
edx_name_affirmation-3.0.2.dist-info/top_level.txt
edx_name_affirmation-3.0.2.dist-info/RECORD
