Metadata-Version: 2.1
Name: edx-name-affirmation
Version: 3.0.2
Summary: Name affirmation app for Open edX
Home-page: https://github.com/edx/edx-name-affirmation
Author: edX
Author-email: oscm@edx.org
License: AGPL 3.0
Keywords: Django edx
Classifier: Framework :: Django
Classifier: Framework :: Django :: 4.2
Classifier: Intended Audience :: Developers
Classifier: License :: OSI Approved :: GNU Affero General Public License v3 or later (AGPLv3+)
Classifier: Natural Language :: English
Classifier: Programming Language :: Python :: 3.11
License-File: LICENSE
Requires-Dist: Django>=2.2
Requires-Dist: django-config-models
Requires-Dist: django-model-utils
Requires-Dist: django-simple-history>3.10.0
Requires-Dist: djangorestframework
Requires-Dist: edx-api-doc-tools
Requires-Dist: edx-celeryutils
Requires-Dist: edx-django-utils>=3.12.0
Requires-Dist: edx-drf-extensions
Requires-Dist: edx-toggles
Requires-Dist: openedx-events
